{
  "block_id": "confirmatory-2026-05-26-b029",
  "block_name": "block-confirmatory-2026-05-26-b029-mlc-i2c-contention",
  "pipeline": "mlc",
  "condition": "i2c-contention",
  "duration_sec": 300,
  "btest": false,
  "started_at": "2026-05-26T15:46:05.355003",
  "mlc_config_header": "mlc_motion_w75.h",
  "silicon_liveness_mlc_src": "0x04",
  "tegrastats_pid_file": "/tmp/tegrastats_pid_confirmatory-2026-05-26-b029.txt",
  "sync_edge_jetson_monotonic_ns": 10358110023590,
  "pipeline_pid": 50633,
  "pipeline_alive_after_init": true,
  "sensor_reachable_after_init": true,
  "contention_start_jetson_monotonic_ns": 10363541668004,
  "cpu_verification_passed": true,
  "cpu_verification_output": "I2C contention: 3 active i2c_hammer processes (target: 3)\nI2C-CONTENTION verify: PASS",
  "pipeline_exit_code": 124,
  "throttling_events": 0,
  "throttling_sample_lines": [],
  "jc_eff_pct": 100.0,
  "jc_eff_n_samples": 3618,
  "jc_eff_threshold_pct": 99.0,
  "jc_eff_passed": true,
  "included": true,
  "exclusion_reason": "",
  "finished_at": "2026-05-26T15:51:18.337720"
}